spoof.py
spoof-1.5.3.dist-info/LICENSE
spoof-1.5.3.dist-info/METADATA
spoof-1.5.3.dist-info/WHEEL
spoof-1.5.3.dist-info/top_level.txt
spoof-1.5.3.dist-info/RECORD
